{"playtime": [2399, 2056], "frostbite": [7094, 5914], "barnabas": [9641, 1250, 1209, 1329], "doomsday": [1231, 1243, 2336], "batman": [2, 971], "sporadically": [11600, 1251, 1205, 1204], "superposition": [2907, 2696], "elongate": [16347, 5984], "steamship": [4726, 3213], "birthright": [3655, 2331], "palgrave": [14917, 6412], "outcrop": [2293, 4831], "blackstone": [2470, 3593], "stairway": [15773, 399], "nanjing": [18810, 19921], "malabsorption": [17703, 5764], "darken": [15301, 10121], "humming": [1235, 1237, 1208, 1310], "consensual": [1229, 1203, 18831], "transboundary": [6643, 5766], "heatstroke": [3396, 4850], "solvers": [1272, 1266, 1220, 1261], "outperform": [2293, 4092], "claimant": [3150, 0], "painstaking": [2997, 8154], "shorebirds": [5965, 4320], "burnham": [1267, 10525], "lobbyists": [1263, 1214, 1218, 15995], "cheque": [16280, 10412], "bonfire": [16289, 1267], "stockton": [3214, 8599], "alexandre": [4233, 17456], "geophys": [10674, 12279], "internalize": [4076, 1293, 1305], "flagella": [4412, 17351], "eyepiece": [3012, 1262], "superfood": [2907, 2508], "rancho": [3378, 14633], "overproduction": [10001, 1281], "englishmen": [2718, 2441], "candid": [9918, 2330], "upstate": [1281, 1260, 16154], "patrolling": [10099, 303], "hadron": [2297, 1228, 1204, 1294], "radiometric": [856, 7284], "texans": [19196, 1262, 1336], "swordfish": [6617, 39], "paycheck": [2512, 2584], "outnumber": [2293, 1285], "doorstep": [546, 2820], "malthus": [17703, 3278], "toothache": [1138, 13705], "pancake": [424, 4638], "jonson": [11295, 2623], "subtitles": [4102, 1303], "roster": [1321, 1211, 1228, 1322], "overheat": [10001, 3396], "greenbelt": [2814, 5874], "weekday": [1240, 2336], "overtones": [10001, 8737], "civility": [3204, 1203, 1206], "stephan": [2820, 9515], "environmentalism": [3923, 18932], "freshmen": [3493, 2441], "consequential": [1229, 1203, 10852], "anabaptist": [11971, 7738], "phonology": [2598, 1222, 1338], "earthworm": [1268, 130], "empathize": [6837, 1293, 1305], "tangles": [10677, 7725], "thickets": [5171, 16507], "microstructure": [8253, 3475], "wherefore": [1247, 1262, 1316, 1252], "skyrocketed": [3859, 6058], "overlaid": [10001, 4514], "introns": [8024, 1228, 1204, 1294], "portrayals": [1228, 1327, 1203, 1252], "dietrich": [4453, 3273], "fearsome": [1331, 9927], "petersen": [3348, 1290, 1209, 1212], "evaporative": [13477, 1230, 1206], "paramilitary": [1285, 1237, 1235, 2706], "phenomenology": [5824, 1222, 1338], "bestselling": [2351, 3565], "personhood": [1202, 8684], "afterschool": [9941, 174], "streetcar": [2624, 2473], "solace": [1272, 1266, 1220, 1261], "constitutive": [6584, 1230, 1206], "summarise": [5105, 1293, 1305], "outgrow": [2293, 1280], "livescience": [1238, 2832], "supplanted": [16500, 17871], "mingled": [1208, 1310, 2845], "landmass": [9978, 3369], "greenfield": [2814, 2653], "hydrostatic": [10295, 6204], "warlike": [1297, 9944], "biogeography": [10023, 1222, 1268, 1247], "bioethics": [10023, 5467], "eruptive": [14187, 1230, 1206], "repelled": [1302, 1232, 1305, 2845], "linings": [10998, 11695], "landlocked": [9978, 637], "calvary": [11516, 4828], "foretold": [1262, 1316, 1252, 1200], "hutton": [148, 8599], "chairperson": [916, 1202], "moderna": [4215, 1333, 1238], "subtitle": [4102, 1303], "cornstarch": [5053, 8730], "burdensome": [5535, 9927], "virginity": [6539, 1203, 1206], "positivism": [1216, 1221, 1206], "multicast": [4620, 3602], "congressmen": [3282, 2441], "asthmatic": [5114, 18823], "antipsychotic": [3031, 13698], "maladaptive": [17703, 6804], "earhart": [5041, 10962], "claimants": [3150, 0], "finale": [9426, 13917], "taipei": [11652, 18858], "proudhon": [3646, 14199], "thereupon": [2299, 2834], "retrofitting": [19449, 7719], "climatology": [3880, 1222, 1338], "intervertebral": [1220, 1247, 12102], "subsoil": [4102, 1268], "sagebrush": [7768, 5802], "lordship": [2862, 3213], "microservices": [8253, 2590], "touchscreen": [1233, 3436], "comedian": [2358, 9627], "lansing": [1209, 1329, 1324, 1281], "antisemitism": [3031, 12468], "photoreceptors": [1319, 6274], "mainline": [2656, 1328], "hydrogel": [10295, 7962], "considerate": [3082, 6707], "hypertrophic": [10739, 14117], "bitmap": [2532, 3702], "dryden": [3757, 9538], "midterm": [3533, 2675], "tinged": [8701, 17583], "eurozone": [12052, 6338], "lagged": [1235, 1240, 1203, 17583], "pinyin": [741, 835], "geomagnetic": [10674, 5047], "langston": [12023, 8599], "isometric": [8458, 7284], "thoughtfully": [1221, 3315], "inkjet": [6855, 6471], "proliferative": [16796, 1230, 1206], "newsweek": [2486, 1240], "westport": [1252, 3810], "howling": [2306, 17193], "gingerbread": [588, 349], "timescales": [2056, 3503], "transposition": [6643, 2696], "semicircular": [4772, 1275], "sterilize": [9219, 1293, 1305], "chinatown": [2857, 2660], "faraway": [1249, 2393], "backend": [2320, 9956], "monmouth": [12505, 1052], "teammates": [2384, 397], "thermoelectric": [1326, 1339], "outstretched": [2293, 8096], "housework": [1796, 2332], "quizlet": [7009, 2402], "interception": [11655, 6986], "neonates": [13556, 6707], "contraindications": [15473, 8732], "backlog": [2320, 5691], "underpinned": [10002, 16801], "seabird": [2943, 6], "infrastructural": [18042, 4914], "bluegrass": [2806, 5113], "groundhog": [1268, 12973], "walleye": [2984, 3012], "harmonize": [6474, 1293, 1305], "counterattack": [4493, 2870], "solaris": [1272, 1266, 1220, 1261], "handel": [9515, 6403], "polycarbonate": [12708, 9258], "doubleday": [3040, 2336], "taoism": [14989, 18932], "herbivorous": [18092, 1236, 1259], "overthrew": [10001, 9013], "abalone": [1250, 1209, 1329, 10733], "saplings": [9611, 17193], "serrated": [14921, 2798], "seaport": [2943, 3810], "seismicity": [8263, 1203, 1206], "heatwave": [3396, 4275], "marshy": [6636, 9764], "bullion": [6656, 6986], "surmounted": [10667, 657], "steinberg": [12350, 14053], "bluefin": [2806, 9426], "dickson": [3919, 2623], "zealanders": [12057, 19649], "toenails": [8256, 661], "multipurpose": [4620, 3351], "neurosurgery": [12323, 4228], "hypersonic": [10739, 13117], "timescale": [2056, 3503], "polaris": [16469, 18230], "theodor": [2269, 8196], "reflexology": [1210, 1306, 1222, 1338], "mallet": [17703, 2402], "macrophage": [9794, 12362], "extruded": [18933, 11653], "outgrowth": [2293, 1280], "hideous": [4613, 1236, 1259], "loophole": [535, 600], "houseplant": [1796, 1278], "proofread": [3935, 2427], "leachate": [12028, 6707], "surpasses": [10667, 5608], "improvise": [3610, 1293, 1305], "sandpaper": [5073, 2925], "printmaking": [4623, 2425], "denounce": [9538, 10089], "skimming": [14887, 1208, 1310], "fireball": [1267, 2967], "unionist": [2908, 15995], "coventry": [10724, 4025], "consulate": [12437, 6707], "counterpoint": [4493, 2426], "bigfoot": [1218, 945], "neoliberal": [10056, 4083], "conservationist": [4933, 15995], "pastoralists": [1324, 1321, 1327, 1329], "creationist": [1281, 15995], "hamstrings": [10525, 6733], "valerie": [18275, 10810], "misbehavior": [12678, 3943], "misaligned": [12678, 7313], "jordanian": [4758, 9627], "gifford": [16509, 4801], "malone": [17703, 672], "stupidity": [3197, 1203, 1206], "rafters": [11413, 19664], "heartbreaking": [2588, 3754], "retroviruses": [19449, 5115], "employability": [6608, 9984], "hatfield": [4651, 2653], "gameplay": [2372, 2399], "cinematic": [515, 18823], "hitchcock": [17917, 16891], "rotted": [8317, 9501], "kimball": [4378, 2967], "calder": [11516, 6125], "webcam": [3783, 1286, 1242], "burnside": [1267, 9960], "charon": [18109, 1228, 1204, 1294], "broadleaf": [4637, 259], "outing": [2293, 11695], "cardiopulmonary": [12797, 6872], "chiapas": [9401, 2094], "parasitism": [7875, 1221, 1206], "beatings": [3033, 11695], "mentorship": [8902, 3213], "seahorse": [2943, 60], "cordial": [11986, 10307], "antipsychotics": [3031, 13698], "diversions": [1322, 1210, 1202, 6476], "viscount": [11139, 1285], "ionian": [6986, 9627], "neurodegeneration": [12323, 7935], "superfoods": [2907, 2508], "airship": [1269, 3213], "cottonwood": [5306, 898], "monoculture": [11818, 2989], "crackdown": [7321, 2347], "rapidity": [4998, 1203, 1206], "flippers": [8927, 2476], "flowchart": [3989, 840], "geochemistry": [10674, 1222, 1265, 1293], "corinthian": [15007, 9627], "areata": [9908, 18710], "alsace": [1252, 1336, 10625], "carlton": [7872, 8599], "foresters": [1262, 1316, 1252, 1200], "dampen": [5896, 701], "surrealism": [10667, 9881], "bushfire": [2079, 1267], "undernourished": [10002, 14639], "earthworks": [1268, 2613], "barbarous": [7863, 1236, 1259], "veracity": [11114, 2395], "chipping": [6307, 11668], "config": [1229, 1203, 2042], "transmembrane": [6643, 5420], "carmichael": [2473, 2899], "neurogenesis": [12323, 1915], "panelists": [13776, 2620], "appreciative": [3752, 1230, 1206], "windward": [1269, 6858], "firepower": [1267, 1302], "workhouse": [2332, 1796], "recursion": [16391, 6986], "conferring": [1250, 1323, 1310, 1203], "autoimmunity": [7873, 5997], "heartfelt": [2588, 2813], "bothering": [10862, 9934], "wendell": [17361, 15186], "underprivileged": [10002, 7165], "undercooked": [10002, 365], "wearables": [3248, 1255], "starship": [2728, 3213], "photoelectric": [1319, 1339], "reformist": [4668, 15995], "downwind": [2347, 1269], "bethany": [11342, 2317], "unionists": [2908, 15995], "strategist": [3781, 1202, 1230], "visualise": [1337, 1293, 1305], "metacognition": [10028, 7595], "tarbush": [9408, 2079], "sundown": [1685, 2347], "bioscience": [10023, 2832], "unabridged": [14190, 3656], "intron": [8024, 1228, 1204, 1294], "secularists": [6618, 15995], "biogeochemical": [10023, 18067], "echolocation": [8751, 1247], "tradeoffs": [1298, 2339], "muskets": [11399, 16507], "armada": [3787, 2050], "goldenrod": [4028, 7409], "brewster": [12543, 19664], "linden": [10998, 9538], "formality": [4863, 1203, 1206], "tamper": [18281, 2476], "sinkholes": [7157, 600], "marcia": [6636, 10353], "flagstaff": [4412, 2906], "netscape": [3703, 6003], "nanostructures": [10072, 3475], "universalist": [5075, 15995], "screenplay": [3436, 2399], "supercritical": [2907, 3489], "microbiologist": [8253, 8400], "grapevine": [8786, 8914], "factbook": [9964, 2487], "archdiocese": [6834, 10740], "withered": [1227, 1323, 1302, 1324], "thyself": [6624, 2647], "antihistamine": [3031, 12200], "thinned": [5099, 18910], "constricted": [1229, 1203, 5901], "mouthparts": [1052, 2926], "metadatashow": [9411, 2382], "soundtrack": [2788, 3026], "longfellow": [2353, 3696], "unilever": [19169, 1262, 1323, 1272], "portage": [3810, 2574], "hamstring": [10525, 5199], "hilltop": [3528, 211], "wildland": [3595, 9978], "bandits": [3221, 2309], "oliveira": [679, 11317], "permutation": [2476, 6311], "bushfires": [2079, 1267], "videotape": [2494, 5945], "heretic": [9934, 18823], "penang": [701, 19442], "marred": [6636, 2578], "bilingualism": [10205, 18932], "parkland": [2766, 9978], "lengthwise": [3675, 4782], "slammed": [15954, 6344], "deliberative": [8471, 1230, 1206], "laymen": [4163, 2441], "surreal": [10667, 2403], "pullman": [3536, 971], "fordham": [4801, 10525], "append": [3386, 9956], "galway": [12871, 399], "passageway": [4892, 399], "radiographic": [856, 5981], "watergate": [1266, 5984], "calais": [11516, 19115], "barron": [3177, 1228, 1204, 1294], "mainframe": [2656, 4413], "neurotoxin": [12323, 9420], "firefly": [1267, 43], "springboard": [3245, 2649], "scarborough": [9872, 11219], "herniation": [12407, 16478], "filmmaking": [2701, 2425], "triage": [11388, 2574], "adamant": [4441, 0], "knitted": [11736, 9501], "woodstock": [898, 3214], "failings": [4290, 11695], "policymaking": [2754, 2425], "radicalism": [5679, 18932], "counterclockwise": [4493, 11611], "sociocultural": [10027, 3722], "materialist": [9985, 15995], "peatland": [9212, 9978], "macromolecules": [9794, 5065], "pegged": [12125, 17583], "repelling": [1302, 1232, 1305, 17193], "marchers": [10693, 2300], "merton": [18884, 8599], "fundamentalism": [4821, 18932], "sharealike": [2710, 1311], "towing": [14293, 11695], "zoologist": [1277, 1211, 1313, 1202, 1230], "leningrad": [10628, 17683], "gearbox": [6117, 2968], "touchdown": [1233, 2347], "undercut": [10002, 2651], "cornwallis": [5053, 18602], "misdiagnosis": [12678, 4959], "evaluative": [5117, 1230, 1206], "domesday": [7899, 2336], "superconductors": [2907, 10722], "alliteration": [9926, 12368], "roundabout": [1275, 9922], "psychometric": [15308, 7284], "expressway": [3988, 399], "percutaneous": [2476, 12336], "dalits": [18559, 2309], "audiovisual": [5267, 1337], "monomers": [11818, 18734], "foreclosure": [1262, 1316, 1252, 1200], "cistern": [13009, 17400], "checksum": [2584, 10010], "basaltic": [8155, 18823], "microrna": [8253, 1333, 1238], "industrialists": [3890, 15995], "materialize": [9985, 1293, 1305], "surrealist": [10667, 18121], "clapping": [18368, 11668], "overcast": [10001, 3602], "subtleties": [6346, 4777], "hermitage": [14851, 2574], "freemasons": [2391, 8529], "tagore": [6447, 7949], "pharmacol": [15854, 8994], "billings": [2778, 11695], "tradeoff": [1298, 2339], "biophysics": [10023, 1222, 1232, 1324], "headway": [2440, 399], "capping": [4737, 11668], "errands": [17690, 2271], "hydrodynamic": [10295, 5170], "floodwaters": [5231, 1266], "geostationary": [10674, 8969], "irregularity": [6653, 1203, 1206], "waterlogged": [1266, 10452], "futility": [13164, 1203, 1206], "grossman": [6090, 971], "vermin": [19960, 7178], "taoist": [14989, 15995], "staffordshire": [14719, 15860], "playlist": [2399, 2620], "gallows": [12871, 2567], "noblemen": [6388, 2441], "expressionism": [4558, 18932], "shutterstock": [1240, 1315, 3214], "totalitarianism": [15216, 18932], "billboards": [2778, 2649], "vandals": [3653, 18559], "electromagnetism": [11946, 12000], "princesses": [1118, 15338], "flywheel": [43, 212], "substandard": [4102, 3005], "mountaintop": [1268, 1218, 1250, 211], "earmarked": [5041, 2007], "biomaterials": [10023, 3642], "bagpipes": [3599, 6233], "bogged": [12637, 17583], "starboard": [2728, 2649], "specter": [15316, 19664], "sidelines": [9960, 3163], "godhead": [2409, 2440], "unicellular": [19169, 5443], "elderberry": [7187, 9498], "oxidize": [6277, 1293, 1305], "redshift": [2578, 4474], "psychopathology": [15308, 7889], "criminality": [3721, 1203, 1206], "suboptimal": [4102, 5631], "cadets": [1200, 1201, 1202, 16507], "overworked": [10001, 2774], "republicanism": [3936, 18932], "hayward": [7162, 6858], "andover": [2271, 10001], "neurobiological": [12323, 4811], "maclean": [1998, 6684], "grievous": [18032, 1236, 1259], "roadblocks": [9974, 3332], "energize": [1324, 1293, 1305], "waxing": [7035, 11695], "coliform": [7499, 2586], "blackbird": [2470, 6], "medusa": [6344, 3620], "pairwise": [3847, 4782], "superhuman": [2907, 2552], "lawfully": [1295, 3315], "greenway": [2814, 399], "prosocial": [3193, 9963], "overwatering": [10001, 1266], "initialize": [3840, 1293, 1305], "proportionality": [7996, 1203, 1206], "barclay": [3177, 5370], "sikhism": [11856, 18932], "parlance": [9324, 12952], "biomolecules": [10023, 5065], "superstructure": [2907, 3475], "dieback": [1239, 2320], "misspelled": [12678, 7879], "lionfish": [71, 39], "corrode": [11986, 10857], "neotropical": [10056, 123], "cargill": [2473, 11163], "statisticians": [1255, 1229, 1325, 1338], "rollout": [3739, 2293], "rationalize": [6113, 1293, 1305], "stalinist": [2054, 15995], "midlife": [3533, 1238], "rankin": [3378, 1200, 1201, 1202], "buttermilk": [354, 4089], "hangover": [4331, 10001], "regretted": [1235, 1210, 1237, 1331], "wanders": [12371, 6125], "misrepresentation": [12678, 5207], "daydreaming": [2336, 3261], "campground": [3601, 1268], "laplace": [1252, 1262, 1200, 1201], "armpits": [3787, 9462], "mistreated": [12678, 3908], "battleground": [1297, 1268], "contestants": [4642, 0], "energetically": [8675, 1251, 1205, 1204], "biosafety": [10023, 3121], "furrow": [6639, 4341], "monash": [12505, 6021], "neuropsychiatric": [12323, 7033], "wayside": [399, 9960], "lunchtime": [4087, 2056], "lucknow": [3267, 9939], "jammed": [10718, 6344], "mealtime": [4913, 2056], "ladybugs": [3160, 12], "seepage": [1225, 2828], "anthers": [0, 2300], "arming": [3787, 11695], "toenail": [8256, 661], "chadwick": [12669, 18511], "nanowires": [10072, 6680], "coronaviruses": [1276, 1270, 1337, 1274], "monochromatic": [11818, 16740], "blackfoot": [2470, 945], "lymphedema": [7401, 11073], "clergymen": [8604, 2441], "antichrist": [3031, 3603], "geotechnical": [10674, 3743], "fanfare": [3229, 10696], "marlowe": [6636, 15418], "thermoplastic": [1326, 4767], "stepwise": [2820, 4782], "allergist": [5675, 1202, 1230], "winslow": [2525, 3439], "tapeworms": [5945, 130], "thunderbolt": [1330, 1206, 675], "subroutine": [4102, 5121], "cyberattacks": [6832, 3979], "mirage": [11820, 2574], "eyewear": [3012, 3248], "linearity": [5337, 1203, 1206], "plaintext": [5356, 3050], "insurgent": [10706, 6924], "proquest": [3193, 7236], "anagrams": [11971, 5936], "rootstock": [588, 3214], "ketoacidosis": [17235, 17148], "derbyshire": [13609, 15860], "peculiarity": [8002, 1203, 1206], "subsidize": [16064, 1293, 1305], "finalize": [2616, 1293, 1305], "decryption": [19248, 6986], "neurocognitive": [12323, 4974], "microalgae": [8253, 5920], "stillbirth": [2342, 3655], "maggots": [16751, 2344], "bridegroom": [9225, 1262, 1202], "orchestration": [9821, 16478], "forebears": [1262, 1316, 1252, 1200], "overgrazing": [10001, 7102], "deterred": [10687, 2578], "anabaptists": [11971, 7738], "electroplating": [11946, 4571], "antacids": [0, 5045], "lincolnshire": [1726, 15860], "intercontinental": [1220, 1247, 6186], "urbanism": [4137, 18932], "pinhole": [741, 600], "leeward": [3803, 6858], "gunshot": [3140, 2685], "normality": [3044, 1203, 1206], "swanson": [120, 2623], "polycyclic": [12708, 11401], "starlight": [2728, 1270], "antenatal": [17871, 11414], "rashid": [14760, 11230], "waterford": [1266, 4801], "denouncing": [9538, 10089], "workman": [2332, 971], "autopilot": [7873, 706], "workday": [2332, 2336], "whiteflies": [2444, 43], "dimming": [543, 1208, 1310], "cubesat": [8698, 4175], "withstood": [9920, 4475], "biosciences": [10023, 2832], "bernhard": [17435, 1272], "inclusivity": [6555, 1203, 1206], "wordnet": [1228, 3703], "offshoot": [2339, 3814], "electromechanical": [11946, 646], "passim": [13024, 14926], "pageant": [2828, 0], "storehouse": [3024, 1796], "militarism": [2706, 1221, 1206], "physiologist": [6721, 1202, 1230], "transcranial": [6643, 1336, 1220, 1261], "sandbox": [5073, 2968], "photoreceptor": [1319, 6671], "gaston": [9982, 8599], "piecemeal": [1262, 4913], "newtown": [2305, 2660], "neuroplasticity": [12323, 11407], "outback": [2293, 2320], "headdress": [2440, 189], "jurist": [7570, 1202, 1230], "characterise": [2839, 1293, 1305], "interlinked": [1220, 1247, 4616], "poliovirus": [9478, 4929], "breastmilk": [4970, 4089], "microflora": [8253, 1278], "fireflies": [1267, 43], "wentworth": [2449, 2775], "triplets": [3305, 4760], "cargoes": [2473, 2680], "nationale": [3346, 13917], "archivist": [6315, 1202, 1230], "artistically": [5906, 1251, 1205, 1204], "kiddos": [3087, 10302], "makerspace": [6295, 5800], "inferring": [1256, 1221, 734], "ashton": [6021, 8599], "magnum": [16751, 15713], "playstation": [2399, 773], "goodall": [1216, 9926], "superconductivity": [2907, 9137], "backside": [2320, 9960], "scrapbook": [1262, 1215, 1219, 1203], "turnbull": [2582, 6656], "secularist": [6618, 15995], "ductwork": [9795, 2332], "neurofeedback": [12323, 4865], "veracruz": [11114, 10298], "hartman": [10962, 971], "misinterpretation": [12678, 5145], "tartan": [9408, 9363], "hissing": [2288, 4628], "dryland": [3757, 9978], "pathogenicity": [1332, 1305, 1203, 1206], "newsroom": [2486, 2520], "tabletop": [2965, 211], "donaldson": [7509, 2623], "withers": [1227, 1323, 1302, 1324], "indira": [15660, 11317], "madeline": [1281, 1328], "malayalam": [19238, 16888], "siphon": [1215, 1219, 14199], "ragtime": [15711, 2056], "tapeworm": [5945, 130], "profusion": [3193, 6581], "superheroes": [2907, 7365], "conceptualize": [6992, 1293, 1305], "whitefly": [2444, 43], "compasses": [10161, 5608], "misunderstand": [12678, 1222], "propelling": [12600, 17193], "intranet": [10653, 3703], "underutilized": [10002, 5902], "dunkirk": [18654, 13189], "theorize": [3356, 1293, 1305], "sewerage": [10181, 2574], "westinghouse": [1252, 1796], "fatherland": [2636, 9978], "kimchi": [4378, 9401], "expelling": [13391, 17193], "folktales": [6322, 6709], "localize": [2490, 1293, 1305], "flashback": [5765, 2320], "weekdays": [1240, 2396], "suckling": [1205, 1279, 17193], "chalice": [18109, 9248], "multilevel": [4620, 631], "mustang": [2381, 19442], "rollover": [3739, 10001], "holistically": [7422, 1251, 1205, 1204], "interwar": [1220, 1247, 1297], "assassinate": [18216, 6707], "upsurge": [1281, 1260, 7556], "foreshadowing": [1262, 1316, 1252, 1200], "overheated": [10001, 1326], "homegrown": [1300, 4030], "wrappers": [7891, 2476], "lancelot": [12952, 2397], "filamentous": [11548, 1236, 1259], "campsite": [3601, 1247], "woefully": [18278, 3315], "subculture": [4102, 2989], "janice": [4757, 604], "snowmelt": [4097, 7395], "profuse": [6814, 2355], "henson": [11207, 2623], "heavyweight": [1329, 9981], "seniority": [3244, 1203, 1206], "sternberg": [1252, 1262, 14053], "barbarism": [7863, 1221, 1206], "formosa": [2586, 13883], "polyvinyl": [12708, 12562], "piglets": [96, 4760], "monomer": [11818, 18884], "outings": [2293, 11695], "hardworking": [1272, 2479], "halide": [17592, 14007], "aftershocks": [9941, 1236, 1217, 1331], "ghanaian": [1921, 9627], "belarusian": [13330, 9627], "overeat": [10001, 1279], "violinist": [867, 15995], "purebred": [4169, 9082], "sourcebook": [2789, 2487], "chagas": [18109, 9982], "bobcats": [4190, 16], "windpipe": [1269, 5682], "extrasolar": [3096, 4676], "simian": [14926, 9627], "gramsci": [9320, 6967], "godwin": [2409, 2525], "stalingrad": [2054, 17683], "retroviral": [19449, 5423], "stallion": [12764, 6986], "constrict": [1229, 1203, 5901], "vanessa": [16219, 19258], "overexposure": [10001, 4927], "metacognitive": [10028, 4974], "chechen": [16280, 8821], "superoxide": [2907, 6277], "bradbury": [14242, 10646], "microfinance": [8253, 4116], "kneecap": [5639, 4737], "telnet": [9369, 3703], "intermarriage": [1220, 1247, 3268], "cartoonist": [1227, 1302, 1324, 15995], "dunlap": [18654, 1252, 1262, 1200], "ramparts": [1974, 2926], "mugabe": [4, 15612], "agrobacterium": [12861, 9117], "storybook": [2478, 2487], "cubism": [14624, 18932], "bailout": [11350, 2293], "erikson": [13740, 2623], "chalkboard": [1333, 1273, 2649], "scandalous": [1209, 1329, 1323, 1236, 1259], "zoroastrianism": [19489, 18932], "choreography": [18740, 1304, 1338], "sinkhole": [7157, 600], "vargas": [11143, 9982], "canvases": [9918, 18452], "triplet": [3305, 2402], "collie": [8994, 3462], "pronouncements": [1320, 1220, 1247, 6787], "airbags": [1269, 206], "dichotomous": [14998, 1236, 1259], "mormonism": [9313, 18932], "warhead": [1297, 2440], "giveaway": [2374, 2393], "familysearch": [935, 3144], "lovelace": [1330, 12610], "dropbox": [3083, 2968], "archduke": [6834, 5881], "endocrinologist": [9389, 1202, 1338], "forestall": [3926, 9926], "biosensors": [10023, 5320], "thermocouple": [1326, 2717], "hartmann": [10962, 11250], "sandalwood": [210, 898], "guitarist": [843, 15995], "jamming": [10718, 1208, 1310], "aground": [12861, 8037], "rebate": [19019, 6707], "substation": [4102, 773], "backcountry": [2320, 2458], "commend": [17254, 9956], "canoeing": [1215, 1219, 1270, 1271], "biochemist": [10023, 10549], "demonstrative": [4873, 1230, 1206], "airframe": [1269, 4413], "backflow": [2320, 3989], "foreskin": [1262, 1316, 1252, 1200], "hallowed": [17592, 15418], "watchman": [816, 971], "antislavery": [3031, 4907], "downstairs": [2347, 9165], "vetted": [7450, 9501], "geomorphology": [10674, 8441], "litany": [7959, 2317], "concurrency": [1229, 1203, 536], "blackmail": [2470, 3845], "timestamp": [2056, 7799], "chaste": [18109, 18794], "pieter": [410, 19664], "skimmed": [14887, 6344], "overdrive": [10001, 2809], "homeschoolers": [1300, 16917], "billboard": [2778, 2649], "porters": [15135, 19664], "cisterns": [13009, 19369], "bulbous": [633, 1236, 1259], "nightfall": [2398, 2810], "whitehall": [2444, 3368], "seafaring": [2943, 10696], "statistician": [1255, 1229, 1325, 1338], "searing": [2943, 734], "parentage": [4466, 2574], "patriarchate": [11241, 6707], "hanford": [9515, 4801], "cremated": [19555, 397], "electrophysiology": [11946, 6721], "shortwave": [2571, 4275], "oxfordshire": [1900, 15860], "intercellular": [1220, 1247, 5443], "roswell": [1321, 1211, 1228, 1322], "photocopy": [1319, 3662], "chainsaw": [4110, 2563], "lifelike": [1238, 9944], "earplugs": [5041, 7414], "gaping": [5088, 11695], "potion": [387, 6986], "brokerage": [3415, 9835], "boyhood": [912, 8684], "neurosurgeon": [12323, 6621], "nominative": [19219, 1230, 1206], "pigmentosa": [1325, 13883], "littlefield": [1219, 2653], "anselm": [1262, 1336, 1218, 1264], "monochrome": [11818, 1272, 1265, 1333], "penchant": [701, 12616], "paddock": [7852, 10760], "firemen": [1267, 2441], "quinine": [12981, 3372], "novartis": [8643, 16057], "intentionality": [9115, 1203, 1206], "entwined": [16786, 3784], "anyhow": [2317, 2306], "leeches": [3803, 16280], "songwriter": [2639, 3976], "potholes": [387, 600], "collated": [8994, 2560], "comstock": [10161, 3214], "multicenter": [4620, 2715], "woodson": [898, 2623], "interrelationships": [1220, 1247, 4001], "metabolically": [5615, 1251, 1205, 1204], "sandhill": [5073, 3528], "knowles": [1222, 7725], "airbag": [1269, 3599], "contraband": [15473, 3221], "odessa": [16429, 19258], "microvascular": [8253, 6818], "protea": [3193, 3821], "superbugs": [2907, 12], "ginsberg": [15996, 14053], "manchu": [971, 14454], "plummet": [12193, 2879], "shockwave": [5674, 4275], "overhanging": [10001, 4331], "mendelian": [16134, 9627], "womanhood": [1151, 8684], "winemaking": [3784, 2425], "quartermaster": [3854, 3209], "erasure": [1244, 2383], "fuelling": [3836, 17193], "passivity": [5946, 1203, 1206], "undercover": [10002, 2890], "survivorship": [6358, 6107], "essayist": [4941, 15995], "industrialist": [3890, 15995], "procreation": [3193, 1281], "neuroendocrine": [12323, 9389], "planktonic": [14705, 11318], "subcategories": [4102, 1206], "protectionism": [3430, 18932], "suitcase": [3938, 2421], "wasteland": [3571, 9978], "bantam": [4540, 18281], "eyewitnesses": [3012, 7412], "wintertime": [3327, 2056], "novella": [6150, 17351], "specialise": [2564, 1293, 1305], "edwardian": [4700, 9627], "deliverables": [4549, 1255], "rationalist": [6113, 15995], "valour": [18275, 2310], "waveguide": [4275, 3730], "hardwired": [1272, 9383], "generality": [1211, 1203, 1206], "woodwork": [898, 2332], "hostname": [3668, 1303], "psychodynamic": [15308, 5170], "radians": [18267, 9627], "jarring": [8571, 734], "timings": [4778, 11695], "sightseeing": [1225, 2981], "ramses": [1974, 15338], "mealtimes": [4913, 2056], "elastin": [16785, 8701], "freddie": [9164, 1239], "undergrowth": [10002, 1280], "riverbank": [3002, 132], "disneyland": [8725, 9978], "centerline": [2715, 1328], "ecuadorian": [10226, 9627], "bittersweet": [6781, 3277], "semicolon": [4772, 6175], "rhineland": [11391, 9978], "alanine": [1262, 1276, 1277, 1335], "foolproof": [10117, 3935], "goldfields": [2747, 4329], "cretan": [19555, 9363], "hyperloop": [10739, 535], "thoroughbred": [6395, 9082], "multifunctional": [4620, 4859], "triton": [11388, 8599], "denton": [9538, 8599], "understatement": [10002, 3127], "microgreens": [8253, 2814], "multiverse": [4620, 5869], "nosebleeds": [1055, 11134], "upshot": [1281, 1260, 1326], "goodyear": [1216, 2333], "behaviorism": [3943, 18932], "winfield": [2525, 2653], "earthenware": [15830, 11880], "janssen": [4757, 1290, 1209, 1212], "tribesmen": [5307, 2441], "genbank": [6579, 132], "desirous": [1223, 1236, 1259], "marsden": [5093, 9538], "readout": [2427, 2293], "deadlock": [1239, 4762], "thrusters": [14549, 19664], "royale": [9689, 13917], "grandchild": [3263, 917], "nearshore": [1248, 5965], "understated": [10002, 1702], "theism": [2269, 18932], "watertight": [1266, 4479], "hairline": [2896, 1328], "blackbirds": [2470, 4320], "rajput": [15210, 2389], "rundown": [2455, 2347], "asceticism": [17638, 18932], "stockholders": [3214, 1315, 1203], "repeatability": [858, 9984], "barents": [3177, 16786], "airlift": [1269, 5996], "electrophysiological": [11946, 6124], "seatbelt": [748, 5874], "incursion": [13966, 6986], "jackfruit": [3529, 4456], "interglacial": [1220, 1247, 9633], "eggshells": [374, 770], "thermonuclear": [1326, 3808], "printout": [4623, 2293], "bodyweight": [1205, 9981], "bonfires": [16289, 1267], "sanitize": [20122, 1293, 1305], "glassware": [3422, 11880], "cossacks": [15664, 1316, 1273], "greyhound": [6127, 19241], "authentically": [6941, 1251, 1205, 1204], "tenfold": [2966, 7452], "milford": [18260, 4801], "airfoil": [1269, 1262, 1273], "captors": [4737, 13693], "desertion": [1268, 1326, 1314, 6986], "canteen": [9918, 6209], "hearsay": [1226, 1227], "housewife": [1796, 2676], "rapeseed": [7329, 4982], "brandeis": [1215, 1219, 1265, 1236], "sourdough": [10319, 8987], "saucepan": [8650, 424], "slaveholders": [5286, 1315, 1203], "landers": [1209, 1329, 1324, 1281], "sportsmen": [3196, 2441], "wikisource": [9550, 2789], "outpouring": [2293, 7629], "megafauna": [11287, 1277], "parson": [9324, 2623], "lynchings": [1239, 1305, 11695], "undernutrition": [10002, 1279], "carolingian": [10236, 9627], "spurring": [1227, 1201, 1203, 734], "stallions": [12764, 6476], "ryegrass": [10766, 5113], "madden": [3768, 9538], "pseudoscience": [10664, 2832], "transgene": [6643, 4944], "cartographer": [1329, 1277, 1213, 1202, 1304], "chemotherapeutic": [17497, 5706], "triphosphate": [11388, 8559], "conspired": [1229, 1203, 18937], "solidity": [1272, 1203, 1206], "ellsworth": [20064, 2775], "gastroenterologist": [17178, 1202, 1230], "raindrops": [3900, 3083], "homecoming": [1300, 2506], "newberry": [2305, 9498], "covington": [1266, 1215, 1219, 1205], "corset": [11986, 1294], "roommate": [2520, 397], "clockwork": [459, 2332], "subsist": [4102, 15995], "tsarist": [1242, 1237, 15995], "armpit": [3787, 7453], "peacebuilding": [3018, 2602], "airspeed": [1269, 3080], "screenwriter": [3436, 3976], "lockwood": [4762, 898], "bothers": [10862, 2300], "hazelnuts": [13132, 675], "marten": [6636, 2966], "ashland": [6021, 9978], "digitize": [9806, 1293, 1305], "narayan": [17001, 16556], "mobilise": [3425, 1293, 1305], "guesswork": [2749, 2332], "altman": [11164, 971], "universalism": [5075, 18932], "retrovirus": [19449, 4929], "forefoot": [1262, 1316, 1252, 1200], "sympathize": [9614, 1293, 1305], "microclimate": [8253, 3880], "autodesk": [7873, 7626], "shamanism": [19514, 18932], "classicism": [3827, 18932], "bradshaw": [14242, 10868], "brainchild": [3178, 917], "butternut": [354, 675], "ragweed": [15711, 6938], "subnational": [4102, 2442], "seahorses": [2943, 60], "clipboard": [8141, 2649], "fairchild": [3084, 917], "railings": [634, 11695], "cometh": [10161, 17610], "foresaw": [1262, 1316, 1252, 1200], "napkins": [11717, 1200, 1201, 1202], "sawing": [2563, 11695], "outbound": [2293, 5488], "veganism": [9251, 18932], "altarpiece": [7472, 1262], "ashram": [6021, 1974], "flashy": [15842, 9764], "undervalued": [10002, 2791], "straus": [20031, 18978], "woodcut": [898, 2651], "elitist": [6895, 1202, 1230], "horseman": [60, 971], "capsid": [4737, 19210], "commotion": [10161, 1232], "snowden": [4097, 9538], "wildcat": [3595, 16], "hornets": [713, 16507], "votive": [2853, 1230, 1206], "bioterrorism": [10023, 7479], "hydrogels": [10295, 7962], "middletown": [2738, 2660], "functionalism": [4859, 18932], "overhang": [10001, 4331], "peroxidase": [2476, 17877], "incentivize": [7944, 1293, 1305], "knotted": [619, 9501], "brookhaven": [1251, 1335, 1205, 1268], "overtook": [10001, 2443], "peruse": [2476, 2355], "confound": [1229, 1203, 2380], "levelled": [631, 2845], "generalist": [9391, 2620], "outsource": [2293, 2789], "martens": [6636, 2966], "motherland": [2657, 9978], "underparts": [10002, 2926], "signalled": [4260, 2845], "fluvial": [5070, 17504], "underwood": [10002, 898], "norwalk": [3643, 2909], "scrutinize": [1324, 1203, 1293, 1305], "silkworm": [6619, 130], "cummins": [15690, 7178], "medlineplus": [15088, 9986], "interviewers": [1220, 1247, 959], "membranous": [5420, 1236, 1259], "patrolled": [10099, 3739], "scammers": [15095, 18734], "respectability": [3000, 9984], "ericsson": [7315, 2623], "leakey": [15878, 616], "sacrum": [10588, 13249], "counterbalance": [4493, 1290], "paleontological": [7044, 16165], "dunedin": [13036, 11331], "psalmist": [8948, 15995], "keypad": [616, 7852], "bookshelf": [2487, 7021], "downplay": [2347, 2399], "overexpression": [10001, 4558], "pallas": [14917, 8080], "worthington": [2775, 8599], "middleware": [2738, 11880], "fintech": [9426, 3972], "hither": [2534, 2300], "calvinist": [10960, 15995], "timeout": [2056, 2293], "intramuscular": [10653, 7386], "oneida": [672, 12302], "hangings": [4331, 11695], "johnstone": [2529, 3593], "habitability": [5777, 9984], "snapchat": [8918, 4448], "lethality": [8418, 1203, 1206], "shimon": [13465, 12505], "geometrically": [7916, 1251, 1205, 1204], "publically": [2413, 1251, 1205, 1204], "bacchus": [14731, 14454], "spanking": [6126, 2752], "carefree": [2415, 2391], "menses": [2441, 15338], "firework": [1267, 2332], "rehabilitative": [19087, 1230, 1206], "authoritarianism": [1302, 1200, 1201, 1202], "farmworkers": [3726, 3174], "pindar": [741, 15301], "seasonings": [2460, 11695], "sipping": [1215, 1219, 11668], "wildcard": [3595, 2969], "freudian": [9758, 9627], "philology": [10999, 1222, 1338], "horseradish": [60, 17853], "engrossed": [13376, 7678], "truthfully": [1229, 3315], "driftwood": [8459, 898], "innings": [1255, 1209, 1329, 1247], "whomever": [3447, 2385], "webcast": [3783, 3602], "gallatin": [12871, 1681], "statuses": [11996, 3357], "skylab": [3859, 198], "rowling": [4341, 17193], "multiracial": [4620, 5162], "evolutionist": [1238, 1293, 1244, 15995], "neuropsychology": [12323, 1222, 1224, 1221], "frankfort": [3729, 5071], "collectivist": [5415, 1202, 1230], "prostatic": [3193, 6204], "bloomsbury": [7686, 10646], "hydrochloride": [10295, 7830], "overshoot": [10001, 3814], "stingrays": [10627, 3967], "contraindicated": [15473, 4908], "subclinical": [4102, 4740], "blotches": [16369, 16280], "slippers": [7984, 2476], "tempera": [13012, 1244], "mildred": [5177, 2578], "formalism": [4863, 18932], "breadfruit": [349, 4456], "publius": [1270, 1271, 1329, 9476], "airing": [1269, 11695], "kantian": [8776, 9627], "multifocal": [4620, 7635], "calluses": [2439, 3357], "scarecrow": [1329, 1331, 1237, 1250], "hyperinflation": [10739, 5882], "songbird": [2639, 6], "organist": [1262, 1336, 1210, 1277], "fillmore": [4158, 9925], "borderlands": [3913, 1268], "silkworms": [6619, 130], "carrington": [12454, 8599], "lading": [17784, 11695], "situate": [10070, 6707], "wanton": [12371, 8599], "backfire": [2320, 1267], "magnetically": [5047, 1251, 1205, 1204], "ravana": [17639, 11971], "buzzword": [11140, 1228], "hobbyist": [1240, 1209, 1212, 1322], "amyloidosis": [1265, 1333, 1279, 18608], "mapreduce": [3702, 3813], "peacekeepers": [3018, 12359], "medallion": [7867, 71], "collectivism": [5415, 1221, 1206], "forsake": [9921, 421], "antiwar": [3031, 1297], "biosolids": [10023, 1272], "skyrocketing": [3859, 6058], "campsites": [3601, 3778], "bittorrent": [2532, 18586], "warlords": [1297, 2862], "perjury": [2476, 7570], "herpesvirus": [7931, 4929], "eyebrow": [3012, 16567], "nebulous": [1265, 1333, 1266, 1236, 1259], "speciality": [2564, 1203, 1206], "housewives": [1796, 7876], "mayflies": [1254, 43], "adaption": [5661, 6986], "alicia": [7670, 10353], "chagall": [18109, 11924], "turkana": [17501, 11971], "keyhole": [616, 600], "traditionalist": [3477, 15995], "combatant": [4490, 0], "gelatinous": [13517, 1236, 1259], "snowstorm": [4097, 4098], "rayleigh": [3967, 14686], "billionaires": [3714, 13660], "frenchmen": [1624, 2441], "marlin": [6636, 10998], "supplant": [16500, 0], "liftoff": [5996, 2339], "framingham": [4413, 10525], "westernmost": [3052, 2324], "bandwagon": [3221, 1316, 1204, 1277], "heartwood": [2588, 898], "radiograph": [856, 5658], "multidrug": [4620, 3365], "woodcock": [898, 16891], "honeymoon": [387, 1684], "bagged": [3599, 17583], "mongoose": [12505, 591], "intermolecular": [1220, 1247, 4847], "clarkson": [2046, 2623], "corroded": [11986, 10857], "watercourses": [1266, 2480], "alderman": [17723, 971], "expedited": [13010, 5957], "francophone": [10762, 2598], "manfred": [971, 9164], "casings": [13640, 11695], "dumbbell": [4608, 480], "pennington": [8833, 8599], "malala": [17703, 1262, 1276, 1277], "legalize": [1295, 1293, 1305], "daybreak": [2336, 2732], "equalize": [1290, 1293, 1305], "deutschland": [18412, 9978], "napping": [11717, 11668], "perigee": [19600, 18861], "stonework": [3593, 2332], "retrofitted": [19449, 7324], "magpie": [16751, 410], "neoliberalism": [10056, 1204, 1294], "systemically": [6433, 1251, 1205, 1204], "silverman": [3567, 971], "standoff": [2801, 2339], "landmines": [9978, 2975], "turfgrass": [10683, 5113], "prostheses": [3193, 2321], "fingernail": [954, 661], "psychomotor": [15308, 4660], "nestlings": [37, 17193]}